{
  "project_info": {
    "project_number": "171753064353",
    "project_id": "blood-donor-11668",
    "storage_bucket": "blood-donor-11668.appspot.com"
  },
  "client": [
    {
      "client_info": {
        "mobilesdk_app_id": "1:171753064353:android:7657ed524de1f70c4b6de0",
        "android_client_info": {
          "package_name": "com.example.blood_doner"
        }
      },
      "oauth_client": [
        {
          "client_id": "171753064353-l92hjhnk9p77tj4bed99g7q3blksstsu.apps.googleusercontent.com",
          "client_type": 1,
          "android_info": {
            "package_name": "com.example.blood_doner",
            "certificate_hash": "ac7c0777c851f1cc9bedebafa0ac05d4b4691fcf"
          }
        },
        {
          "client_id": "171753064353-srr9plo2qgmu10e95374hmocbibiln45.apps.googleusercontent.com",
          "client_type": 1,
          "android_info": {
            "package_name": "com.example.blood_doner",
            "certificate_hash": "2e4fbf708653c7f8ce106979846db6dc8383b020"
          }
        },
        {
          "client_id": "171753064353-krmieduaugedufva6ifqgc19lq5t34kk.apps.googleusercontent.com",
          "client_type": 3
        }
      ],
      "api_key": [
        {
          "current_key": "AIzaSyDVuEHGsc0a0Ahzd7rBLGVRAExXcys-EeQ"
        }
      ],
      "services": {
        "appinvite_service": {
          "other_platform_oauth_client": [
            {
              "client_id": "171753064353-krmieduaugedufva6ifqgc19lq5t34kk.apps.googleusercontent.com",
              "client_type": 3
            }
          ]
        }
      }
    }
  ],
  "configuration_version": "1"
}